{
  "source_file": "data/extracted/2015-wave3/Demographic_Background.dta",
  "source_sha1": "f0b327a97b908e1bddc2d8360ba856c4b19f6711",
  "source_backend": "pyreadstat",
  "row_count": 21095,
  "column_count": 81,
  "columns": [
    "ID",
    "householdID",
    "communityID",
    "ba000_w2_3",
    "ba004_w3",
    "ba004_w3_1",
    "ba004_w3_2",
    "ba004_w3_3",
    "ba002",
    "ba002_1",
    "ba002_2",
    "ba002_3",
    "ba003",
    "bb000_w3",
    "bb000_w3_1",
    "bb000_w3_2",
    "bb001_w3",
    "bb001_w3_1",
    "bb001_w3_2",
    "bb003",
    "bb004",
    "bb005",
    "bb005_w3_1",
    "bb005_w3_2",
    "bb001",
    "bc001_w3_1",
    "bc001_w3_2",
    "bc001_w3_3",
    "bc002_w3",
    "bc002_w3_1",
    "bc002_w3_2",
    "bc002_w3_3_1",
    "bc002_w3_3_2",
    "bc002_w3_5",
    "bc002_w3_6_1",
    "bc002_w3_6_2",
    "bd001_w2_4",
    "bd001_w3_1",
    "bd002_w3",
    "bd006",
    "bd007_w2_1s1",
    "bd007_w2_1s2",
    "bd007_w2_1s3",
    "bd007_w2_1s4",
    "bd007_w2_1s5",
    "bd007_w2_1s6",
    "bd007_w2_1s7",
    "bd007_w2_1s8",
    "bd008_w2_1",
    "bd009_w2_1",
    "bd010",
    "bd011",
    "bd012",
    "bd013",
    "bd014",
    "be001",
    "be003_w2_1",
    "be009_1",
    "be009_2",
    "bf001",
    "bf002_1",
    "bf002_2",
    "bf003",
    "bf004",
    "bf004_w3_1",
    "bf005_1",
    "bf005_2",
    "bf006_1",
    "bf006_2",
    "bf006_w2_1",
    "bf006_w2_2_1",
    "bf006_w2_2_2",
    "bf006_w2_3",
    "bf006_w2_4",
    "bf007_1",
    "bf007_2",
    "bf008",
    "bf009",
    "bf010",
    "xrtype",
    "versionID"
  ],
  "file_label": "Demographic Background",
  "file_encoding": null,
  "notes": [],
  "column_labels": [
    "Individual ID",
    "Household ID",
    "Community ID",
    "Gender",
    "Birth Time on ID Card or Hukou",
    "Birth Time on ID Card or Hukou:Year",
    "Birth Time on ID Card or Hukou:Month",
    "Birth Time on ID Card or Hukou:Day",
    "When were Your Born",
    "When were You Born: Year",
    "When were You Born: Month",
    "When were You Born: Day",
    "Solar or Lunar Calendar",
    "What's Your Address in The Time of Last Interview",
    "What's The Type of The Address",
    "Was It Village or City/Town",
    "What's Your Address Now",
    "What's The Type of The Address",
    "Was It Village or City/Town",
    "When Did You First Live in This County/City/District",
    "First Moved to Permanent Address, Did You Live in The Same Village/Community as",
    "In Which Year Did You First Live In this Village/Community",
    "Would You Change Your Address in Next Two Years?",
    "Where Would Your New Address?",
    "Where Were You Born",
    "Your Hukou Type and Your Hukou Location Are Right?",
    "What's Your Hukou Type in Last Interview",
    "What's Your Hukou Location in Last Interview",
    "Since [ZIWTime], Have Your Hukou Type and Location Changed",
    "Your Hukou Type This Time?",
    "The Reason Why Hukou Type Changed",
    "When Your Hukou Type Changed:Year",
    "When Your Hukou Type Changed:Month",
    "Why Your Hukou Location Changed",
    "When Your Hukou Location Changed:Year",
    "When Your Hukou Location Changed:Month",
    "Have Your Highest Level of Education Changed?",
    "Are You Literate?",
    "How Many Years at School after [BD001_W2_4]",
    "At What Age Did You Finish Schooling",
    "Have You Ever Attended School for Adult Education Since Last Interview?",
    "Have You Ever Attended School for Adult Education Since Last Interview?",
    "Have You Ever Attended School for Adult Education Since Last Interview?",
    "Have You Ever Attended School for Adult Education Since Last Interview?",
    "Have You Ever Attended School for Adult Education Since Last Interview?",
    "Have You Ever Attended School for Adult Education Since Last Interview?",
    "Have You Ever Attended School for Adult Education Since Last Interview?",
    "Have You Ever Attended School for Adult Education Since Last Interview?",
    "How Many Years Did You Spend in Adult Edu Since Last Interview",
    "Did You Get Diploma or Degree from The Adult Education Since from Last Interview",
    "When Did You Receive The Diploma",
    "What Is The Highest Adult Education Degree",
    "Have Your Attend Vocational and Tec. Training since [ZIWTime]",
    "How Many Times Have You Accepted Training",
    "How Many Years Have You Been Trained Since [ZIWTime]",
    "Martial Status",
    "How Many Times Have You Been Married Since Last Interview?",
    "When Was Your Most Recent Marriage: Year",
    "When Was Your Most Recent Marriage: Month",
    "Your Spouse/Partner's Chinese Zodiac Sign",
    "When Was Your Spouse Born: Year",
    "When Was Your Spouse Born: Month",
    "Your Spouse/Partner's Birthday: Solar Calendar or Lunar Calendar",
    "Your Spouse's Highest Level of Education",
    "Is Your Spouse Literate?",
    "When Did You Seperate: Year",
    "When Did You Seperate: Month",
    "When Did You Divorce: Year",
    "When Did You Divorce: Month",
    "Reason of Divorce",
    "Divided Assets: You Got",
    "Divided Assets: Ex-wife/Husband Got",
    "Do You Have Any Infancy Children? Owed to Whom",
    "How Much Money You or Your Ex-wife/husband Pay for Upbringing The Children",
    "When Did Your Spouse Pass Away: Year",
    "When Did Your Spouse Pass Away: Month",
    "How Ofen Did The Respondent Receive Assistance",
    "What Is Your Relationship to R",
    "What Is The Main Reason for Proxy",
    "R Interview Type",
    "Version ID"
  ],
  "column_names_to_labels": {
    "ID": "Individual ID",
    "householdID": "Household ID",
    "communityID": "Community ID",
    "ba000_w2_3": "Gender",
    "ba004_w3": "Birth Time on ID Card or Hukou",
    "ba004_w3_1": "Birth Time on ID Card or Hukou:Year",
    "ba004_w3_2": "Birth Time on ID Card or Hukou:Month",
    "ba004_w3_3": "Birth Time on ID Card or Hukou:Day",
    "ba002": "When were Your Born",
    "ba002_1": "When were You Born: Year",
    "ba002_2": "When were You Born: Month",
    "ba002_3": "When were You Born: Day",
    "ba003": "Solar or Lunar Calendar",
    "bb000_w3": "What's Your Address in The Time of Last Interview",
    "bb000_w3_1": "What's The Type of The Address",
    "bb000_w3_2": "Was It Village or City/Town",
    "bb001_w3": "What's Your Address Now",
    "bb001_w3_1": "What's The Type of The Address",
    "bb001_w3_2": "Was It Village or City/Town",
    "bb003": "When Did You First Live in This County/City/District",
    "bb004": "First Moved to Permanent Address, Did You Live in The Same Village/Community as",
    "bb005": "In Which Year Did You First Live In this Village/Community",
    "bb005_w3_1": "Would You Change Your Address in Next Two Years?",
    "bb005_w3_2": "Where Would Your New Address?",
    "bb001": "Where Were You Born",
    "bc001_w3_1": "Your Hukou Type and Your Hukou Location Are Right?",
    "bc001_w3_2": "What's Your Hukou Type in Last Interview",
    "bc001_w3_3": "What's Your Hukou Location in Last Interview",
    "bc002_w3": "Since [ZIWTime], Have Your Hukou Type and Location Changed",
    "bc002_w3_1": "Your Hukou Type This Time?",
    "bc002_w3_2": "The Reason Why Hukou Type Changed",
    "bc002_w3_3_1": "When Your Hukou Type Changed:Year",
    "bc002_w3_3_2": "When Your Hukou Type Changed:Month",
    "bc002_w3_5": "Why Your Hukou Location Changed",
    "bc002_w3_6_1": "When Your Hukou Location Changed:Year",
    "bc002_w3_6_2": "When Your Hukou Location Changed:Month",
    "bd001_w2_4": "Have Your Highest Level of Education Changed?",
    "bd001_w3_1": "Are You Literate?",
    "bd002_w3": "How Many Years at School after [BD001_W2_4]",
    "bd006": "At What Age Did You Finish Schooling",
    "bd007_w2_1s1": "Have You Ever Attended School for Adult Education Since Last Interview?",
    "bd007_w2_1s2": "Have You Ever Attended School for Adult Education Since Last Interview?",
    "bd007_w2_1s3": "Have You Ever Attended School for Adult Education Since Last Interview?",
    "bd007_w2_1s4": "Have You Ever Attended School for Adult Education Since Last Interview?",
    "bd007_w2_1s5": "Have You Ever Attended School for Adult Education Since Last Interview?",
    "bd007_w2_1s6": "Have You Ever Attended School for Adult Education Since Last Interview?",
    "bd007_w2_1s7": "Have You Ever Attended School for Adult Education Since Last Interview?",
    "bd007_w2_1s8": "Have You Ever Attended School for Adult Education Since Last Interview?",
    "bd008_w2_1": "How Many Years Did You Spend in Adult Edu Since Last Interview",
    "bd009_w2_1": "Did You Get Diploma or Degree from The Adult Education Since from Last Interview",
    "bd010": "When Did You Receive The Diploma",
    "bd011": "What Is The Highest Adult Education Degree",
    "bd012": "Have Your Attend Vocational and Tec. Training since [ZIWTime]",
    "bd013": "How Many Times Have You Accepted Training",
    "bd014": "How Many Years Have You Been Trained Since [ZIWTime]",
    "be001": "Martial Status",
    "be003_w2_1": "How Many Times Have You Been Married Since Last Interview?",
    "be009_1": "When Was Your Most Recent Marriage: Year",
    "be009_2": "When Was Your Most Recent Marriage: Month",
    "bf001": "Your Spouse/Partner's Chinese Zodiac Sign",
    "bf002_1": "When Was Your Spouse Born: Year",
    "bf002_2": "When Was Your Spouse Born: Month",
    "bf003": "Your Spouse/Partner's Birthday: Solar Calendar or Lunar Calendar",
    "bf004": "Your Spouse's Highest Level of Education",
    "bf004_w3_1": "Is Your Spouse Literate?",
    "bf005_1": "When Did You Seperate: Year",
    "bf005_2": "When Did You Seperate: Month",
    "bf006_1": "When Did You Divorce: Year",
    "bf006_2": "When Did You Divorce: Month",
    "bf006_w2_1": "Reason of Divorce",
    "bf006_w2_2_1": "Divided Assets: You Got",
    "bf006_w2_2_2": "Divided Assets: Ex-wife/Husband Got",
    "bf006_w2_3": "Do You Have Any Infancy Children? Owed to Whom",
    "bf006_w2_4": "How Much Money You or Your Ex-wife/husband Pay for Upbringing The Children",
    "bf007_1": "When Did Your Spouse Pass Away: Year",
    "bf007_2": "When Did Your Spouse Pass Away: Month",
    "bf008": "How Ofen Did The Respondent Receive Assistance",
    "bf009": "What Is Your Relationship to R",
    "bf010": "What Is The Main Reason for Proxy",
    "xrtype": "R Interview Type",
    "versionID": "Version ID"
  },
  "value_labels": {
    "bb004": {
      "1": "1 Yes",
      "2": "2 No"
    },
    "ba000_w2_3": {
      "1": "1 male",
      "2": "2 female"
    },
    "bc001_w3_1": {
      "1": "1 Yes",
      "2": "2 No"
    },
    "bb005_w3_1": {
      "1": "1 Yes",
      "2": "2 No"
    },
    "bf001": {
      "1": "1 Rat",
      "2": "2 Ox",
      "3": "3 Tiger",
      "4": "4 Rabbit",
      "5": "5 Dragon",
      "6": "6 Snake",
      "7": "7 Horse",
      "8": "8 Goat",
      "9": "9 Monkey",
      "10": "10 Rooster",
      "11": "11 Dog",
      "12": "12 Pig"
    },
    "bd009_w2_1": {
      "1": "1 Yes",
      "2": "2 No"
    },
    "bd012": {
      "1": "1 Yes",
      "2": "2 No"
    },
    "bf004_w3_1": {
      "1": "1 Yes",
      "2": "2 No"
    },
    "xrtype": {
      "1": "1 NEWIW New Interview",
      "2": "2 REIW Followup Interview",
      "3": "3 EXITIW Exit Interview"
    },
    "ba004_w3": {
      "1": "1 Year Month Day",
      "2": "2 Not Having Hukou or ID Card"
    },
    "ba002": {
      "1": "1 The Same with Hukou or ID Card",
      "2": "2 Year Month Day"
    },
    "ba003": {
      "1": "1 Solar Calendar",
      "2": "2 Lunar Calendar"
    },
    "bb000_w3": {
      "1": "1 Address in Last Interview",
      "2": "2 Other Places",
      "3": "Abroad"
    },
    "bb000_w3_1": {
      "1": "1 Family Housing",
      "2": "2 Nursing Home",
      "3": "3 Hospital",
      "4": "4 Other"
    },
    "bb000_w3_2": {
      "1": "1 Main City Zone",
      "2": "2 Combination Zone Between Urban and Rural Areas",
      "3": "3 The Town Center",
      "4": "4 ZhenXiang Area",
      "5": "5 Special Area",
      "6": "6 Township Central",
      "7": "7 Village"
    },
    "bb001_w3": {
      "1": "1 ZLocation",
      "2": "2 Other Province/City/County Township Villiage/Neiborhood",
      "3": "3 Abroad"
    },
    "bb001_w3_1": {
      "1": "1 Family Housing",
      "2": "2 Nursing Home",
      "3": "3 Hospital",
      "4": "4 Other"
    },
    "bb001_w3_2": {
      "1": "1 Main City Zone",
      "2": "2 Combination Zone Between Urban and Rural Areas",
      "3": "3 The Town Center",
      "4": "4 ZhenXiang Area",
      "5": "5 Special Area",
      "6": "6 Township Central",
      "7": "7 Village"
    },
    "bb005_w3_2": {
      "1": "1 I Am Not Sure",
      "2": "2 Another House in The Same Village/Community",
      "3": "3 Other",
      "4": "4 Abroad"
    },
    "bb001": {
      "1": "1 The Same as Permanent Address",
      "2": "2 Another Village/Neighborhood in Permanent Address's County/City/District",
      "3": "3 Other County/City/District",
      "4": "4 Abroad"
    },
    "bc001_w3_2": {
      "1": "1 Agricultual Hukou",
      "2": "2 Non-agricultural Hukou",
      "3": "3 Unified Residence Hukou",
      "4": "4 Do Not Have Hukou"
    },
    "bc001_w3_3": {
      "1": "1 The Same as Permanent Address",
      "16": "16 Another Village/Neighborhood in Permanent Address's County/City/District",
      "17": "17 Abroad"
    },
    "bc002_w3": {
      "1": "1 Hukou Type Changed",
      "2": "2 Hukou Location Changed",
      "3": "3 Both Changed",
      "4": "4 None Changed"
    },
    "bc002_w3_1": {
      "1": "1 Agricultual Hukou",
      "2": "2 Non-agricultural Hukou",
      "3": "3 Unified Residence Hukou",
      "4": "4 Do Not Have Hukou"
    },
    "bc002_w3_2": {
      "1": "1 Schooling",
      "2": "2 Marriage",
      "3": "3 Career",
      "4": "4 Land Expropriation",
      "5": "5 Whole Village Relocation",
      "6": "6 Other"
    },
    "bc002_w3_5": {
      "1": "1 Schooling",
      "2": "2 Marriage",
      "3": "3 Career",
      "4": "4 Land Expropriation",
      "5": "5 Whole Village Relocation"
    },
    "bd001_w2_4": {
      "1": "1 No Formal Education (Illiterate)",
      "2": "2 Did Not Finish Primary School But Capable of Reading/Writing",
      "3": "3 Sichu/Home School",
      "4": "4 Elementary School",
      "5": "5 Middle School",
      "6": "6 High School",
      "7": "7 Vocational School",
      "8": "8 Two/Three Year College/Associate Degree",
      "9": "9 Four-year College/Bachelor's Degree",
      "10": "10 Master's Degree",
      "11": "11 Doctoral Degree",
      "12": "12 No Change"
    },
    "bd001_w3_1": {
      "1": "1 Yes",
      "2": "2 No"
    },
    "bd007_w2_1s1": {
      "1": "1 None",
      "2": "2 TV University",
      "3": "3 Night School",
      "4": "4 Zikao",
      "5": "5 Hanshou",
      "6": "6 Literacy Course",
      "7": "7 Accelerated Education Course",
      "8": "8 Other"
    },
    "bd007_w2_1s2": {
      "1": "1 None",
      "2": "2 TV University",
      "3": "3 Night School",
      "4": "4 Zikao",
      "5": "5 Hanshou",
      "6": "6 Literacy Course",
      "7": "7 Accelerated Education Course",
      "8": "8 Other"
    },
    "bd007_w2_1s3": {
      "1": "1 None",
      "2": "2 TV University",
      "3": "3 Night School",
      "4": "4 Zikao",
      "5": "5 Hanshou",
      "6": "6 Literacy Course",
      "7": "7 Accelerated Education Course",
      "8": "8 Other"
    },
    "bd007_w2_1s4": {
      "1": "1 None",
      "2": "2 TV University",
      "3": "3 Night School",
      "4": "4 Zikao",
      "5": "5 Hanshou",
      "6": "6 Literacy Course",
      "7": "7 Accelerated Education Course",
      "8": "8 Other"
    },
    "bd007_w2_1s5": {
      "1": "1 None",
      "2": "2 TV University",
      "3": "3 Night School",
      "4": "4 Zikao",
      "5": "5 Hanshou",
      "6": "6 Literacy Course",
      "7": "7 Accelerated Education Course",
      "8": "8 Other"
    },
    "bd007_w2_1s6": {
      "1": "1 None",
      "2": "2 TV University",
      "3": "3 Night School",
      "4": "4 Zikao",
      "5": "5 Hanshou",
      "6": "6 Literacy Course",
      "7": "7 Accelerated Education Course",
      "8": "8 Other"
    },
    "bd007_w2_1s7": {
      "1": "1 None",
      "2": "2 TV University",
      "3": "3 Night School",
      "4": "4 Zikao",
      "5": "5 Hanshou",
      "6": "6 Literacy Course",
      "7": "7 Accelerated Education Course",
      "8": "8 Other"
    },
    "bd007_w2_1s8": {
      "1": "1 None",
      "2": "2 TV University",
      "3": "3 Night School",
      "4": "4 Zikao",
      "5": "5 Hanshou",
      "6": "6 Literacy Course",
      "7": "7 Accelerated Education Course",
      "8": "8 Other"
    },
    "bd011": {
      "1": "1 Vocational School",
      "2": "2 Tow/Three Year College / Associate Degree",
      "3": "3 Four Year College / Bachelors Degree",
      "4": "4 Others"
    },
    "be001": {
      "1": "1 Married with Spouse Present",
      "2": "2 Married But Not Living with Spouse Temporarily for Reasons Such as Work",
      "3": "3 Separated",
      "4": "4 Divorced",
      "5": "5 Widowed",
      "6": "6 Never Married",
      "7": "7 Cohabitated"
    },
    "bf003": {
      "1": "1 Solar Calendar",
      "2": "2 Lunar Calendar"
    },
    "bf004": {
      "1": "1 No Formal Education Illiterate",
      "2": "2 Did Not Finish Primary School But Capable of Reading or Writing",
      "3": "3 Sishu/Home School",
      "4": "4 Elementary School",
      "5": "5 Middle School",
      "6": "6 High School",
      "7": "7 Vocational School",
      "8": "8 Two/Three Year College / Associate Degree",
      "9": "9 Four Year College / Bachelors Degree",
      "10": "10 Master's Degree",
      "11": "11 Doctoral Degree/Ph.D"
    },
    "bf006_w2_1": {
      "1": "1 Emotional Feud",
      "2": "2 Live in Different Places",
      "3": "3 In Order to Facilitate The Property Purchase Transactions",
      "4": "4 Other"
    },
    "bf006_w2_3": {
      "1": "1 Myself",
      "2": "2 My Last Spouse",
      "3": "3 None"
    },
    "bf008": {
      "1": "1 Never",
      "2": "2 A Few Times",
      "3": "3 Most or All The Time",
      "4": "4 The Section Was Done by A Proxy Respondent"
    },
    "bf009": {
      "1": "1 Spouse",
      "2": "2 Mother",
      "3": "3 Father",
      "4": "4 Mother-in-law",
      "5": "5 Father-in-law",
      "6": "6 Sibling",
      "7": "7 Brother-in-law/Sister-in-law",
      "8": "8 Child",
      "9": "9 Spouse of Child",
      "10": "10 Grandchild",
      "11": "11 Other Relative",
      "12": "12 Helper or Other Non-relative",
      "13": "13 Others"
    },
    "bf010": {
      "1": "1 The Respondent Has Serious Physical Handicaps",
      "2": "2 The Respondent Has Serious Mental Handicaps",
      "3": "3 The Respondent Has Rejected This Interview",
      "4": "4 Other"
    }
  },
  "variable_to_label": {
    "ba000_w2_3": "ba000_w2_3",
    "ba004_w3": "ba004_w3",
    "ba002": "ba002",
    "ba003": "ba003",
    "bb000_w3": "bb000_w3",
    "bb000_w3_1": "bb000_w3_1",
    "bb000_w3_2": "bb000_w3_2",
    "bb001_w3": "bb001_w3",
    "bb001_w3_1": "bb001_w3_1",
    "bb001_w3_2": "bb001_w3_2",
    "bb004": "bb004",
    "bb005_w3_1": "bb005_w3_1",
    "bb005_w3_2": "bb005_w3_2",
    "bb001": "bb001",
    "bc001_w3_1": "bc001_w3_1",
    "bc001_w3_2": "bc001_w3_2",
    "bc001_w3_3": "bc001_w3_3",
    "bc002_w3": "bc002_w3",
    "bc002_w3_1": "bc002_w3_1",
    "bc002_w3_2": "bc002_w3_2",
    "bc002_w3_5": "bc002_w3_5",
    "bd001_w2_4": "bd001_w2_4",
    "bd001_w3_1": "bd001_w3_1",
    "bd007_w2_1s1": "bd007_w2_1s1",
    "bd007_w2_1s2": "bd007_w2_1s2",
    "bd007_w2_1s3": "bd007_w2_1s3",
    "bd007_w2_1s4": "bd007_w2_1s4",
    "bd007_w2_1s5": "bd007_w2_1s5",
    "bd007_w2_1s6": "bd007_w2_1s6",
    "bd007_w2_1s7": "bd007_w2_1s7",
    "bd007_w2_1s8": "bd007_w2_1s8",
    "bd009_w2_1": "bd009_w2_1",
    "bd011": "bd011",
    "bd012": "bd012",
    "be001": "be001",
    "bf001": "bf001",
    "bf003": "bf003",
    "bf004": "bf004",
    "bf004_w3_1": "bf004_w3_1",
    "bf006_w2_1": "bf006_w2_1",
    "bf006_w2_3": "bf006_w2_3",
    "bf008": "bf008",
    "bf009": "bf009",
    "bf010": "bf010",
    "xrtype": "xrtype"
  },
  "variable_value_labels": {
    "ba000_w2_3": {
      "1": "1 male",
      "2": "2 female"
    },
    "ba004_w3": {
      "1": "1 Year Month Day",
      "2": "2 Not Having Hukou or ID Card"
    },
    "ba002": {
      "1": "1 The Same with Hukou or ID Card",
      "2": "2 Year Month Day"
    },
    "ba003": {
      "1": "1 Solar Calendar",
      "2": "2 Lunar Calendar"
    },
    "bb000_w3": {
      "1": "1 Address in Last Interview",
      "2": "2 Other Places",
      "3": "Abroad"
    },
    "bb000_w3_1": {
      "1": "1 Family Housing",
      "2": "2 Nursing Home",
      "3": "3 Hospital",
      "4": "4 Other"
    },
    "bb000_w3_2": {
      "1": "1 Main City Zone",
      "2": "2 Combination Zone Between Urban and Rural Areas",
      "3": "3 The Town Center",
      "4": "4 ZhenXiang Area",
      "5": "5 Special Area",
      "6": "6 Township Central",
      "7": "7 Village"
    },
    "bb001_w3": {
      "1": "1 ZLocation",
      "2": "2 Other Province/City/County Township Villiage/Neiborhood",
      "3": "3 Abroad"
    },
    "bb001_w3_1": {
      "1": "1 Family Housing",
      "2": "2 Nursing Home",
      "3": "3 Hospital",
      "4": "4 Other"
    },
    "bb001_w3_2": {
      "1": "1 Main City Zone",
      "2": "2 Combination Zone Between Urban and Rural Areas",
      "3": "3 The Town Center",
      "4": "4 ZhenXiang Area",
      "5": "5 Special Area",
      "6": "6 Township Central",
      "7": "7 Village"
    },
    "bb004": {
      "1": "1 Yes",
      "2": "2 No"
    },
    "bb005_w3_1": {
      "1": "1 Yes",
      "2": "2 No"
    },
    "bb005_w3_2": {
      "1": "1 I Am Not Sure",
      "2": "2 Another House in The Same Village/Community",
      "3": "3 Other",
      "4": "4 Abroad"
    },
    "bb001": {
      "1": "1 The Same as Permanent Address",
      "2": "2 Another Village/Neighborhood in Permanent Address's County/City/District",
      "3": "3 Other County/City/District",
      "4": "4 Abroad"
    },
    "bc001_w3_1": {
      "1": "1 Yes",
      "2": "2 No"
    },
    "bc001_w3_2": {
      "1": "1 Agricultual Hukou",
      "2": "2 Non-agricultural Hukou",
      "3": "3 Unified Residence Hukou",
      "4": "4 Do Not Have Hukou"
    },
    "bc001_w3_3": {
      "1": "1 The Same as Permanent Address",
      "16": "16 Another Village/Neighborhood in Permanent Address's County/City/District",
      "17": "17 Abroad"
    },
    "bc002_w3": {
      "1": "1 Hukou Type Changed",
      "2": "2 Hukou Location Changed",
      "3": "3 Both Changed",
      "4": "4 None Changed"
    },
    "bc002_w3_1": {
      "1": "1 Agricultual Hukou",
      "2": "2 Non-agricultural Hukou",
      "3": "3 Unified Residence Hukou",
      "4": "4 Do Not Have Hukou"
    },
    "bc002_w3_2": {
      "1": "1 Schooling",
      "2": "2 Marriage",
      "3": "3 Career",
      "4": "4 Land Expropriation",
      "5": "5 Whole Village Relocation",
      "6": "6 Other"
    },
    "bc002_w3_5": {
      "1": "1 Schooling",
      "2": "2 Marriage",
      "3": "3 Career",
      "4": "4 Land Expropriation",
      "5": "5 Whole Village Relocation"
    },
    "bd001_w2_4": {
      "1": "1 No Formal Education (Illiterate)",
      "2": "2 Did Not Finish Primary School But Capable of Reading/Writing",
      "3": "3 Sichu/Home School",
      "4": "4 Elementary School",
      "5": "5 Middle School",
      "6": "6 High School",
      "7": "7 Vocational School",
      "8": "8 Two/Three Year College/Associate Degree",
      "9": "9 Four-year College/Bachelor's Degree",
      "10": "10 Master's Degree",
      "11": "11 Doctoral Degree",
      "12": "12 No Change"
    },
    "bd001_w3_1": {
      "1": "1 Yes",
      "2": "2 No"
    },
    "bd007_w2_1s1": {
      "1": "1 None",
      "2": "2 TV University",
      "3": "3 Night School",
      "4": "4 Zikao",
      "5": "5 Hanshou",
      "6": "6 Literacy Course",
      "7": "7 Accelerated Education Course",
      "8": "8 Other"
    },
    "bd007_w2_1s2": {
      "1": "1 None",
      "2": "2 TV University",
      "3": "3 Night School",
      "4": "4 Zikao",
      "5": "5 Hanshou",
      "6": "6 Literacy Course",
      "7": "7 Accelerated Education Course",
      "8": "8 Other"
    },
    "bd007_w2_1s3": {
      "1": "1 None",
      "2": "2 TV University",
      "3": "3 Night School",
      "4": "4 Zikao",
      "5": "5 Hanshou",
      "6": "6 Literacy Course",
      "7": "7 Accelerated Education Course",
      "8": "8 Other"
    },
    "bd007_w2_1s4": {
      "1": "1 None",
      "2": "2 TV University",
      "3": "3 Night School",
      "4": "4 Zikao",
      "5": "5 Hanshou",
      "6": "6 Literacy Course",
      "7": "7 Accelerated Education Course",
      "8": "8 Other"
    },
    "bd007_w2_1s5": {
      "1": "1 None",
      "2": "2 TV University",
      "3": "3 Night School",
      "4": "4 Zikao",
      "5": "5 Hanshou",
      "6": "6 Literacy Course",
      "7": "7 Accelerated Education Course",
      "8": "8 Other"
    },
    "bd007_w2_1s6": {
      "1": "1 None",
      "2": "2 TV University",
      "3": "3 Night School",
      "4": "4 Zikao",
      "5": "5 Hanshou",
      "6": "6 Literacy Course",
      "7": "7 Accelerated Education Course",
      "8": "8 Other"
    },
    "bd007_w2_1s7": {
      "1": "1 None",
      "2": "2 TV University",
      "3": "3 Night School",
      "4": "4 Zikao",
      "5": "5 Hanshou",
      "6": "6 Literacy Course",
      "7": "7 Accelerated Education Course",
      "8": "8 Other"
    },
    "bd007_w2_1s8": {
      "1": "1 None",
      "2": "2 TV University",
      "3": "3 Night School",
      "4": "4 Zikao",
      "5": "5 Hanshou",
      "6": "6 Literacy Course",
      "7": "7 Accelerated Education Course",
      "8": "8 Other"
    },
    "bd009_w2_1": {
      "1": "1 Yes",
      "2": "2 No"
    },
    "bd011": {
      "1": "1 Vocational School",
      "2": "2 Tow/Three Year College / Associate Degree",
      "3": "3 Four Year College / Bachelors Degree",
      "4": "4 Others"
    },
    "bd012": {
      "1": "1 Yes",
      "2": "2 No"
    },
    "be001": {
      "1": "1 Married with Spouse Present",
      "2": "2 Married But Not Living with Spouse Temporarily for Reasons Such as Work",
      "3": "3 Separated",
      "4": "4 Divorced",
      "5": "5 Widowed",
      "6": "6 Never Married",
      "7": "7 Cohabitated"
    },
    "bf001": {
      "1": "1 Rat",
      "2": "2 Ox",
      "3": "3 Tiger",
      "4": "4 Rabbit",
      "5": "5 Dragon",
      "6": "6 Snake",
      "7": "7 Horse",
      "8": "8 Goat",
      "9": "9 Monkey",
      "10": "10 Rooster",
      "11": "11 Dog",
      "12": "12 Pig"
    },
    "bf003": {
      "1": "1 Solar Calendar",
      "2": "2 Lunar Calendar"
    },
    "bf004": {
      "1": "1 No Formal Education Illiterate",
      "2": "2 Did Not Finish Primary School But Capable of Reading or Writing",
      "3": "3 Sishu/Home School",
      "4": "4 Elementary School",
      "5": "5 Middle School",
      "6": "6 High School",
      "7": "7 Vocational School",
      "8": "8 Two/Three Year College / Associate Degree",
      "9": "9 Four Year College / Bachelors Degree",
      "10": "10 Master's Degree",
      "11": "11 Doctoral Degree/Ph.D"
    },
    "bf004_w3_1": {
      "1": "1 Yes",
      "2": "2 No"
    },
    "bf006_w2_1": {
      "1": "1 Emotional Feud",
      "2": "2 Live in Different Places",
      "3": "3 In Order to Facilitate The Property Purchase Transactions",
      "4": "4 Other"
    },
    "bf006_w2_3": {
      "1": "1 Myself",
      "2": "2 My Last Spouse",
      "3": "3 None"
    },
    "bf008": {
      "1": "1 Never",
      "2": "2 A Few Times",
      "3": "3 Most or All The Time",
      "4": "4 The Section Was Done by A Proxy Respondent"
    },
    "bf009": {
      "1": "1 Spouse",
      "2": "2 Mother",
      "3": "3 Father",
      "4": "4 Mother-in-law",
      "5": "5 Father-in-law",
      "6": "6 Sibling",
      "7": "7 Brother-in-law/Sister-in-law",
      "8": "8 Child",
      "9": "9 Spouse of Child",
      "10": "10 Grandchild",
      "11": "11 Other Relative",
      "12": "12 Helper or Other Non-relative",
      "13": "13 Others"
    },
    "bf010": {
      "1": "1 The Respondent Has Serious Physical Handicaps",
      "2": "2 The Respondent Has Serious Mental Handicaps",
      "3": "3 The Respondent Has Rejected This Interview",
      "4": "4 Other"
    },
    "xrtype": {
      "1": "1 NEWIW New Interview",
      "2": "2 REIW Followup Interview",
      "3": "3 EXITIW Exit Interview"
    }
  },
  "original_variable_types": {
    "ID": "%12s",
    "householdID": "%10s",
    "communityID": "%9s",
    "ba000_w2_3": "%8.0g",
    "ba004_w3": "%8.0g",
    "ba004_w3_1": "%8.0g",
    "ba004_w3_2": "%8.0g",
    "ba004_w3_3": "%8.0g",
    "ba002": "%8.0g",
    "ba002_1": "%8.0g",
    "ba002_2": "%8.0g",
    "ba002_3": "%8.0g",
    "ba003": "%8.0g",
    "bb000_w3": "%8.0g",
    "bb000_w3_1": "%8.0g",
    "bb000_w3_2": "%8.0g",
    "bb001_w3": "%8.0g",
    "bb001_w3_1": "%8.0g",
    "bb001_w3_2": "%8.0g",
    "bb003": "%8.0g",
    "bb004": "%8.0g",
    "bb005": "%8.0g",
    "bb005_w3_1": "%8.0g",
    "bb005_w3_2": "%8.0g",
    "bb001": "%8.0g",
    "bc001_w3_1": "%8.0g",
    "bc001_w3_2": "%8.0g",
    "bc001_w3_3": "%8.0g",
    "bc002_w3": "%8.0g",
    "bc002_w3_1": "%8.0g",
    "bc002_w3_2": "%8.0g",
    "bc002_w3_3_1": "%8.0g",
    "bc002_w3_3_2": "%8.0g",
    "bc002_w3_5": "%8.0g",
    "bc002_w3_6_1": "%8.0g",
    "bc002_w3_6_2": "%8.0g",
    "bd001_w2_4": "%8.0g",
    "bd001_w3_1": "%8.0g",
    "bd002_w3": "%8.0g",
    "bd006": "%8.0g",
    "bd007_w2_1s1": "%8.0g",
    "bd007_w2_1s2": "%8.0g",
    "bd007_w2_1s3": "%8.0g",
    "bd007_w2_1s4": "%8.0g",
    "bd007_w2_1s5": "%8.0g",
    "bd007_w2_1s6": "%8.0g",
    "bd007_w2_1s7": "%8.0g",
    "bd007_w2_1s8": "%8.0g",
    "bd008_w2_1": "%10.0g",
    "bd009_w2_1": "%8.0g",
    "bd010": "%8.0g",
    "bd011": "%8.0g",
    "bd012": "%8.0g",
    "bd013": "%8.0g",
    "bd014": "%12s",
    "be001": "%8.0g",
    "be003_w2_1": "%8.0g",
    "be009_1": "%8.0g",
    "be009_2": "%8.0g",
    "bf001": "%8.0g",
    "bf002_1": "%8.0g",
    "bf002_2": "%8.0g",
    "bf003": "%8.0g",
    "bf004": "%8.0g",
    "bf004_w3_1": "%8.0g",
    "bf005_1": "%8.0g",
    "bf005_2": "%8.0g",
    "bf006_1": "%8.0g",
    "bf006_2": "%8.0g",
    "bf006_w2_1": "%8.0g",
    "bf006_w2_2_1": "%12.0g",
    "bf006_w2_2_2": "%12.0g",
    "bf006_w2_3": "%8.0g",
    "bf006_w2_4": "%8.0g",
    "bf007_1": "%8.0g",
    "bf007_2": "%8.0g",
    "bf008": "%8.0g",
    "bf009": "%8.0g",
    "bf010": "%8.0g",
    "xrtype": "%8.0g",
    "versionID": "%9s"
  },
  "readstat_variable_types": {
    "ID": "string",
    "householdID": "string",
    "communityID": "string",
    "ba000_w2_3": "int8",
    "ba004_w3": "int8",
    "ba004_w3_1": "int16",
    "ba004_w3_2": "int8",
    "ba004_w3_3": "int8",
    "ba002": "int8",
    "ba002_1": "int16",
    "ba002_2": "int8",
    "ba002_3": "int8",
    "ba003": "int8",
    "bb000_w3": "int8",
    "bb000_w3_1": "int8",
    "bb000_w3_2": "int8",
    "bb001_w3": "int8",
    "bb001_w3_1": "int8",
    "bb001_w3_2": "int8",
    "bb003": "int16",
    "bb004": "int8",
    "bb005": "int16",
    "bb005_w3_1": "int8",
    "bb005_w3_2": "int8",
    "bb001": "int8",
    "bc001_w3_1": "int8",
    "bc001_w3_2": "int8",
    "bc001_w3_3": "int8",
    "bc002_w3": "int8",
    "bc002_w3_1": "int8",
    "bc002_w3_2": "int8",
    "bc002_w3_3_1": "int16",
    "bc002_w3_3_2": "int8",
    "bc002_w3_5": "int8",
    "bc002_w3_6_1": "int16",
    "bc002_w3_6_2": "int8",
    "bd001_w2_4": "int8",
    "bd001_w3_1": "int8",
    "bd002_w3": "int8",
    "bd006": "int8",
    "bd007_w2_1s1": "int8",
    "bd007_w2_1s2": "int8",
    "bd007_w2_1s3": "int8",
    "bd007_w2_1s4": "int8",
    "bd007_w2_1s5": "int8",
    "bd007_w2_1s6": "int8",
    "bd007_w2_1s7": "int8",
    "bd007_w2_1s8": "int8",
    "bd008_w2_1": "double",
    "bd009_w2_1": "int8",
    "bd010": "int16",
    "bd011": "int8",
    "bd012": "int8",
    "bd013": "int16",
    "bd014": "string",
    "be001": "int8",
    "be003_w2_1": "int8",
    "be009_1": "int8",
    "be009_2": "int8",
    "bf001": "int8",
    "bf002_1": "int16",
    "bf002_2": "int8",
    "bf003": "int8",
    "bf004": "int8",
    "bf004_w3_1": "int8",
    "bf005_1": "int16",
    "bf005_2": "int8",
    "bf006_1": "int16",
    "bf006_2": "int8",
    "bf006_w2_1": "int8",
    "bf006_w2_2_1": "int32",
    "bf006_w2_2_2": "int32",
    "bf006_w2_3": "int8",
    "bf006_w2_4": "int16",
    "bf007_1": "int16",
    "bf007_2": "int8",
    "bf008": "int8",
    "bf009": "int8",
    "bf010": "int8",
    "xrtype": "int8",
    "versionID": "string"
  },
  "missing_ranges": {},
  "missing_user_values": {},
  "variable_alignment": {
    "ID": "right",
    "householdID": "right",
    "communityID": "right",
    "ba000_w2_3": "right",
    "ba004_w3": "right",
    "ba004_w3_1": "right",
    "ba004_w3_2": "right",
    "ba004_w3_3": "right",
    "ba002": "right",
    "ba002_1": "right",
    "ba002_2": "right",
    "ba002_3": "right",
    "ba003": "right",
    "bb000_w3": "right",
    "bb000_w3_1": "right",
    "bb000_w3_2": "right",
    "bb001_w3": "right",
    "bb001_w3_1": "right",
    "bb001_w3_2": "right",
    "bb003": "right",
    "bb004": "right",
    "bb005": "right",
    "bb005_w3_1": "right",
    "bb005_w3_2": "right",
    "bb001": "right",
    "bc001_w3_1": "right",
    "bc001_w3_2": "right",
    "bc001_w3_3": "right",
    "bc002_w3": "right",
    "bc002_w3_1": "right",
    "bc002_w3_2": "right",
    "bc002_w3_3_1": "right",
    "bc002_w3_3_2": "right",
    "bc002_w3_5": "right",
    "bc002_w3_6_1": "right",
    "bc002_w3_6_2": "right",
    "bd001_w2_4": "right",
    "bd001_w3_1": "right",
    "bd002_w3": "right",
    "bd006": "right",
    "bd007_w2_1s1": "right",
    "bd007_w2_1s2": "right",
    "bd007_w2_1s3": "right",
    "bd007_w2_1s4": "right",
    "bd007_w2_1s5": "right",
    "bd007_w2_1s6": "right",
    "bd007_w2_1s7": "right",
    "bd007_w2_1s8": "right",
    "bd008_w2_1": "right",
    "bd009_w2_1": "right",
    "bd010": "right",
    "bd011": "right",
    "bd012": "right",
    "bd013": "right",
    "bd014": "right",
    "be001": "right",
    "be003_w2_1": "right",
    "be009_1": "right",
    "be009_2": "right",
    "bf001": "right",
    "bf002_1": "right",
    "bf002_2": "right",
    "bf003": "right",
    "bf004": "right",
    "bf004_w3_1": "right",
    "bf005_1": "right",
    "bf005_2": "right",
    "bf006_1": "right",
    "bf006_2": "right",
    "bf006_w2_1": "right",
    "bf006_w2_2_1": "right",
    "bf006_w2_2_2": "right",
    "bf006_w2_3": "right",
    "bf006_w2_4": "right",
    "bf007_1": "right",
    "bf007_2": "right",
    "bf008": "right",
    "bf009": "right",
    "bf010": "right",
    "xrtype": "right",
    "versionID": "right"
  },
  "variable_storage_width": {
    "ID": 13,
    "householdID": 11,
    "communityID": 8,
    "ba000_w2_3": 1,
    "ba004_w3": 1,
    "ba004_w3_1": 2,
    "ba004_w3_2": 1,
    "ba004_w3_3": 1,
    "ba002": 1,
    "ba002_1": 2,
    "ba002_2": 1,
    "ba002_3": 1,
    "ba003": 1,
    "bb000_w3": 1,
    "bb000_w3_1": 1,
    "bb000_w3_2": 1,
    "bb001_w3": 1,
    "bb001_w3_1": 1,
    "bb001_w3_2": 1,
    "bb003": 2,
    "bb004": 1,
    "bb005": 2,
    "bb005_w3_1": 1,
    "bb005_w3_2": 1,
    "bb001": 1,
    "bc001_w3_1": 1,
    "bc001_w3_2": 1,
    "bc001_w3_3": 1,
    "bc002_w3": 1,
    "bc002_w3_1": 1,
    "bc002_w3_2": 1,
    "bc002_w3_3_1": 2,
    "bc002_w3_3_2": 1,
    "bc002_w3_5": 1,
    "bc002_w3_6_1": 2,
    "bc002_w3_6_2": 1,
    "bd001_w2_4": 1,
    "bd001_w3_1": 1,
    "bd002_w3": 1,
    "bd006": 1,
    "bd007_w2_1s1": 1,
    "bd007_w2_1s2": 1,
    "bd007_w2_1s3": 1,
    "bd007_w2_1s4": 1,
    "bd007_w2_1s5": 1,
    "bd007_w2_1s6": 1,
    "bd007_w2_1s7": 1,
    "bd007_w2_1s8": 1,
    "bd008_w2_1": 8,
    "bd009_w2_1": 1,
    "bd010": 2,
    "bd011": 1,
    "bd012": 1,
    "bd013": 2,
    "bd014": 13,
    "be001": 1,
    "be003_w2_1": 1,
    "be009_1": 1,
    "be009_2": 1,
    "bf001": 1,
    "bf002_1": 2,
    "bf002_2": 1,
    "bf003": 1,
    "bf004": 1,
    "bf004_w3_1": 1,
    "bf005_1": 2,
    "bf005_2": 1,
    "bf006_1": 2,
    "bf006_2": 1,
    "bf006_w2_1": 1,
    "bf006_w2_2_1": 4,
    "bf006_w2_2_2": 4,
    "bf006_w2_3": 1,
    "bf006_w2_4": 2,
    "bf007_1": 2,
    "bf007_2": 1,
    "bf008": 1,
    "bf009": 1,
    "bf010": 1,
    "xrtype": 1,
    "versionID": 9
  },
  "variable_display_width": {
    "ID": 12,
    "householdID": 10,
    "communityID": 9,
    "ba000_w2_3": 8,
    "ba004_w3": 8,
    "ba004_w3_1": 8,
    "ba004_w3_2": 8,
    "ba004_w3_3": 8,
    "ba002": 8,
    "ba002_1": 8,
    "ba002_2": 8,
    "ba002_3": 8,
    "ba003": 8,
    "bb000_w3": 8,
    "bb000_w3_1": 8,
    "bb000_w3_2": 8,
    "bb001_w3": 8,
    "bb001_w3_1": 8,
    "bb001_w3_2": 8,
    "bb003": 8,
    "bb004": 8,
    "bb005": 8,
    "bb005_w3_1": 8,
    "bb005_w3_2": 8,
    "bb001": 8,
    "bc001_w3_1": 8,
    "bc001_w3_2": 8,
    "bc001_w3_3": 8,
    "bc002_w3": 8,
    "bc002_w3_1": 8,
    "bc002_w3_2": 8,
    "bc002_w3_3_1": 8,
    "bc002_w3_3_2": 8,
    "bc002_w3_5": 8,
    "bc002_w3_6_1": 8,
    "bc002_w3_6_2": 8,
    "bd001_w2_4": 8,
    "bd001_w3_1": 8,
    "bd002_w3": 8,
    "bd006": 8,
    "bd007_w2_1s1": 8,
    "bd007_w2_1s2": 8,
    "bd007_w2_1s3": 8,
    "bd007_w2_1s4": 8,
    "bd007_w2_1s5": 8,
    "bd007_w2_1s6": 8,
    "bd007_w2_1s7": 8,
    "bd007_w2_1s8": 8,
    "bd008_w2_1": 10,
    "bd009_w2_1": 8,
    "bd010": 8,
    "bd011": 8,
    "bd012": 8,
    "bd013": 8,
    "bd014": 12,
    "be001": 8,
    "be003_w2_1": 8,
    "be009_1": 8,
    "be009_2": 8,
    "bf001": 8,
    "bf002_1": 8,
    "bf002_2": 8,
    "bf003": 8,
    "bf004": 8,
    "bf004_w3_1": 8,
    "bf005_1": 8,
    "bf005_2": 8,
    "bf006_1": 8,
    "bf006_2": 8,
    "bf006_w2_1": 8,
    "bf006_w2_2_1": 12,
    "bf006_w2_2_2": 12,
    "bf006_w2_3": 8,
    "bf006_w2_4": 8,
    "bf007_1": 8,
    "bf007_2": 8,
    "bf008": 8,
    "bf009": 8,
    "bf010": 8,
    "xrtype": 8,
    "versionID": 9
  },
  "variable_measure": {
    "ID": "unknown",
    "householdID": "unknown",
    "communityID": "unknown",
    "ba000_w2_3": "unknown",
    "ba004_w3": "unknown",
    "ba004_w3_1": "unknown",
    "ba004_w3_2": "unknown",
    "ba004_w3_3": "unknown",
    "ba002": "unknown",
    "ba002_1": "unknown",
    "ba002_2": "unknown",
    "ba002_3": "unknown",
    "ba003": "unknown",
    "bb000_w3": "unknown",
    "bb000_w3_1": "unknown",
    "bb000_w3_2": "unknown",
    "bb001_w3": "unknown",
    "bb001_w3_1": "unknown",
    "bb001_w3_2": "unknown",
    "bb003": "unknown",
    "bb004": "unknown",
    "bb005": "unknown",
    "bb005_w3_1": "unknown",
    "bb005_w3_2": "unknown",
    "bb001": "unknown",
    "bc001_w3_1": "unknown",
    "bc001_w3_2": "unknown",
    "bc001_w3_3": "unknown",
    "bc002_w3": "unknown",
    "bc002_w3_1": "unknown",
    "bc002_w3_2": "unknown",
    "bc002_w3_3_1": "unknown",
    "bc002_w3_3_2": "unknown",
    "bc002_w3_5": "unknown",
    "bc002_w3_6_1": "unknown",
    "bc002_w3_6_2": "unknown",
    "bd001_w2_4": "unknown",
    "bd001_w3_1": "unknown",
    "bd002_w3": "unknown",
    "bd006": "unknown",
    "bd007_w2_1s1": "unknown",
    "bd007_w2_1s2": "unknown",
    "bd007_w2_1s3": "unknown",
    "bd007_w2_1s4": "unknown",
    "bd007_w2_1s5": "unknown",
    "bd007_w2_1s6": "unknown",
    "bd007_w2_1s7": "unknown",
    "bd007_w2_1s8": "unknown",
    "bd008_w2_1": "unknown",
    "bd009_w2_1": "unknown",
    "bd010": "unknown",
    "bd011": "unknown",
    "bd012": "unknown",
    "bd013": "unknown",
    "bd014": "unknown",
    "be001": "unknown",
    "be003_w2_1": "unknown",
    "be009_1": "unknown",
    "be009_2": "unknown",
    "bf001": "unknown",
    "bf002_1": "unknown",
    "bf002_2": "unknown",
    "bf003": "unknown",
    "bf004": "unknown",
    "bf004_w3_1": "unknown",
    "bf005_1": "unknown",
    "bf005_2": "unknown",
    "bf006_1": "unknown",
    "bf006_2": "unknown",
    "bf006_w2_1": "unknown",
    "bf006_w2_2_1": "unknown",
    "bf006_w2_2_2": "unknown",
    "bf006_w2_3": "unknown",
    "bf006_w2_4": "unknown",
    "bf007_1": "unknown",
    "bf007_2": "unknown",
    "bf008": "unknown",
    "bf009": "unknown",
    "bf010": "unknown",
    "xrtype": "unknown",
    "versionID": "unknown"
  },
  "csv_file": "data/curated/2015-wave3/Demographic_Background/Demographic_Background.csv",
  "parquet_file": "data/curated/2015-wave3/Demographic_Background/Demographic_Background.parquet",
  "metadata_file": "data/curated/2015-wave3/Demographic_Background/Demographic_Background.metadata.json",
  "curation_note": "CSV/Parquet 保留原始编码值；变量标签和值标签在 metadata JSON 中。",
  "parquet_string_columns": [
    "ID",
    "householdID",
    "communityID",
    "ba000_w2_3",
    "ba004_w3",
    "ba004_w3_1",
    "ba004_w3_2",
    "ba004_w3_3",
    "ba002",
    "ba002_1",
    "ba002_2",
    "ba002_3",
    "ba003",
    "bb000_w3",
    "bb000_w3_1",
    "bb000_w3_2",
    "bb001_w3",
    "bb001_w3_1",
    "bb001_w3_2",
    "bb003",
    "bb004",
    "bb005",
    "bb005_w3_1",
    "bb005_w3_2",
    "bb001",
    "bc001_w3_1",
    "bc001_w3_2",
    "bc001_w3_3",
    "bc002_w3",
    "bc002_w3_1",
    "bc002_w3_2",
    "bc002_w3_3_1",
    "bc002_w3_3_2",
    "bc002_w3_5",
    "bc002_w3_6_1",
    "bc002_w3_6_2",
    "bd001_w2_4",
    "bd001_w3_1",
    "bd002_w3",
    "bd006",
    "bd007_w2_1s1",
    "bd007_w2_1s2",
    "bd007_w2_1s3",
    "bd007_w2_1s4",
    "bd007_w2_1s5",
    "bd007_w2_1s6",
    "bd007_w2_1s7",
    "bd007_w2_1s8",
    "bd009_w2_1",
    "bd010",
    "bd011",
    "bd012",
    "bd013",
    "bd014",
    "be001",
    "be003_w2_1",
    "be009_1",
    "be009_2",
    "bf001",
    "bf002_1",
    "bf002_2",
    "bf003",
    "bf004",
    "bf004_w3_1",
    "bf005_1",
    "bf005_2",
    "bf006_1",
    "bf006_2",
    "bf006_w2_1",
    "bf006_w2_2_1",
    "bf006_w2_2_2",
    "bf006_w2_3",
    "bf006_w2_4",
    "bf007_1",
    "bf007_2",
    "bf008",
    "bf009",
    "bf010",
    "xrtype",
    "versionID"
  ],
  "parquet_note": "Parquet 要求单列类型稳定；含 Stata 特殊缺失码的 object 列会转成字符串，原始缺失码定义仍记录在 missing_user_values / value_labels 中。"
}